CHANGES.txt
COPYRIGHT.txt
LICENSE.txt
README.txt
ez_setup.py
setup.cfg
setup.py
docs/Makefile
docs/basic.rst
docs/component.rst
docs/conf.py
docs/directives.rst
docs/event.rst
docs/glossary.rst
docs/index.rst
docs/.static/logo_hi.gif
docs/.static/repoze.css
repoze/__init__.py
repoze.component.egg-info/PKG-INFO
repoze.component.egg-info/SOURCES.txt
repoze.component.egg-info/dependency_links.txt
repoze.component.egg-info/entry_points.txt
repoze.component.egg-info/namespace_packages.txt
repoze.component.egg-info/not-zip-safe
repoze.component.egg-info/requires.txt
repoze.component.egg-info/top_level.txt
repoze/component/__init__.py
repoze/component/advice.py
repoze/component/directives.py
repoze/component/registry.py
repoze/component/tests/__init__.py
repoze/component/tests/test_advice.py
repoze/component/tests/test_directives.py
repoze/component/tests/test_registry.py